{
  "displayFieldName" : "",
  "fieldAliases" : {
    "FID" : "FID",
    "FID_AQUA_2" : "FID_AQUA_2",
    "PA_Str" : "PA_Str",
    "DMSLat" : "DMSLat",
    "DMSLon" : "DMSLon",
    "NAME" : "NAME",
    "PA_Str_1" : "PA_Str_1",
    "PA_Num_1" : "PA_Num_1"
  },
  "geometryType" : "esriGeometryPoint",
  "spatialReference" : {
    "wkid" : 4326,
    "latestWkid" : 4326
  },
  "fields" : [
    {
      "name" : "FID",
      "type" : "esriFieldTypeOID",
      "alias" : "FID"
    },
    {
      "name" : "FID_AQUA_2",
      "type" : "esriFieldTypeInteger",
      "alias" : "FID_AQUA_2"
    },
    {
      "name" : "PA_Str",
      "type" : "esriFieldTypeString",
      "alias" : "PA_Str",
      "length" : 3
    },
    {
      "name" : "DMSLat",
      "type" : "esriFieldTypeString",
      "alias" : "DMSLat",
      "length" : 254
    },
    {
      "name" : "DMSLon",
      "type" : "esriFieldTypeString",
      "alias" : "DMSLon",
      "length" : 254
    },
    {
      "name" : "NAME",
      "type" : "esriFieldTypeString",
      "alias" : "NAME",
      "length" : 50
    },
    {
      "name" : "PA_Str_1",
      "type" : "esriFieldTypeString",
      "alias" : "PA_Str_1",
      "length" : 3
    },
    {
      "name" : "PA_Num_1",
      "type" : "esriFieldTypeSmallInteger",
      "alias" : "PA_Num_1"
    }
  ],
  "features" : [
    {
      "attributes" : {
        "FID" : 9,
        "FID_AQUA_2" : -1,
        "PA_Str" : "14",
        "DMSLat" : "04°11'51.46\" LS",
        "DMSLon" : "127°33'15.82\" BT",
        "NAME" : "Titik ZPPI No. 1 (Zona 14)",
        "PA_Str_1" : "14",
        "PA_Num_1" : 14
      },
      "geometry" : {
        "x" : 127.5543971740001,
        "y" : -4.1976279079999284
      }
    },
    {
      "attributes" : {
        "FID" : 10,
        "FID_AQUA_2" : -1,
        "PA_Str" : "14",
        "DMSLat" : "04°04'38.88\" LS",
        "DMSLon" : "127°38'09.47\" BT",
        "NAME" : "Titik ZPPI No. 2 (Zona 14)",
        "PA_Str_1" : "14",
        "PA_Num_1" : 14
      },
      "geometry" : {
        "x" : 127.63596505200005,
        "y" : -4.0774675299999945
      }
    },
    {
      "attributes" : {
        "FID" : 11,
        "FID_AQUA_2" : -1,
        "PA_Str" : "14",
        "DMSLat" : "06°40'08.52\" LS",
        "DMSLon" : "127°56'09.25\" BT",
        "NAME" : "Titik ZPPI No. 3 (Zona 14)",
        "PA_Str_1" : "14",
        "PA_Num_1" : 14
      },
      "geometry" : {
        "x" : 127.93590337700002,
        "y" : -6.6690342969999588
      }
    }
  ]
}