{
  "displayFieldName" : "",
  "fieldAliases" : {
    "FID" : "FID",
    "FID_viirs_" : "FID_viirs_",
    "PA_Str" : "PA_Str",
    "DMSLat" : "DMSLat",
    "DMSLon" : "DMSLon",
    "NAME" : "NAME",
    "PA_Str_1" : "PA_Str_1",
    "PA_Num_1" : "PA_Num_1"
  },
  "geometryType" : "esriGeometryPoint",
  "spatialReference" : {
    "wkid" : 4326,
    "latestWkid" : 4326
  },
  "fields" : [
    {
      "name" : "FID",
      "type" : "esriFieldTypeOID",
      "alias" : "FID"
    },
    {
      "name" : "FID_viirs_",
      "type" : "esriFieldTypeInteger",
      "alias" : "FID_viirs_"
    },
    {
      "name" : "PA_Str",
      "type" : "esriFieldTypeString",
      "alias" : "PA_Str",
      "length" : 3
    },
    {
      "name" : "DMSLat",
      "type" : "esriFieldTypeString",
      "alias" : "DMSLat",
      "length" : 254
    },
    {
      "name" : "DMSLon",
      "type" : "esriFieldTypeString",
      "alias" : "DMSLon",
      "length" : 254
    },
    {
      "name" : "NAME",
      "type" : "esriFieldTypeString",
      "alias" : "NAME",
      "length" : 50
    },
    {
      "name" : "PA_Str_1",
      "type" : "esriFieldTypeString",
      "alias" : "PA_Str_1",
      "length" : 3
    },
    {
      "name" : "PA_Num_1",
      "type" : "esriFieldTypeSmallInteger",
      "alias" : "PA_Num_1"
    }
  ],
  "features" : [
    {
      "attributes" : {
        "FID" : 70,
        "FID_viirs_" : -1,
        "PA_Str" : "6",
        "DMSLat" : "05°18'36.83\" LU",
        "DMSLon" : "122°16'49.39\" BT",
        "NAME" : "Titik ZPPI No. 1 (Zona 6)",
        "PA_Str_1" : "6",
        "PA_Num_1" : 6
      },
      "geometry" : {
        "x" : 122.28038722300008,
        "y" : 5.3102320190000576
      }
    },
    {
      "attributes" : {
        "FID" : 71,
        "FID_viirs_" : -1,
        "PA_Str" : "6",
        "DMSLat" : "05°22'25.21\" LU",
        "DMSLon" : "122°22'26.06\" BT",
        "NAME" : "Titik ZPPI No. 2 (Zona 6)",
        "PA_Str_1" : "6",
        "PA_Num_1" : 6
      },
      "geometry" : {
        "x" : 122.37390784800002,
        "y" : 5.3736722050000765
      }
    },
    {
      "attributes" : {
        "FID" : 72,
        "FID_viirs_" : -1,
        "PA_Str" : "6",
        "DMSLat" : "06°43'15.33\" LU",
        "DMSLon" : "123°32'03.93\" BT",
        "NAME" : "Titik ZPPI No. 3 (Zona 6)",
        "PA_Str_1" : "6",
        "PA_Num_1" : 6
      },
      "geometry" : {
        "x" : 123.53442617000005,
        "y" : 6.7209270700001014
      }
    },
    {
      "attributes" : {
        "FID" : 73,
        "FID_viirs_" : -1,
        "PA_Str" : "6",
        "DMSLat" : "06°08'48.70\" LU",
        "DMSLon" : "123°39'34.75\" BT",
        "NAME" : "Titik ZPPI No. 4 (Zona 6)",
        "PA_Str_1" : "6",
        "PA_Num_1" : 6
      },
      "geometry" : {
        "x" : 123.65965355600011,
        "y" : 6.1468630290000128
      }
    },
    {
      "attributes" : {
        "FID" : 74,
        "FID_viirs_" : -1,
        "PA_Str" : "6",
        "DMSLat" : "06°46'43.62\" LU",
        "DMSLon" : "123°40'01.72\" BT",
        "NAME" : "Titik ZPPI No. 5 (Zona 6)",
        "PA_Str_1" : "6",
        "PA_Num_1" : 6
      },
      "geometry" : {
        "x" : 123.66714508300001,
        "y" : 6.7787843540000416
      }
    },
    {
      "attributes" : {
        "FID" : 75,
        "FID_viirs_" : -1,
        "PA_Str" : "6",
        "DMSLat" : "06°51'04.47\" LU",
        "DMSLon" : "123°42'24.43\" BT",
        "NAME" : "Titik ZPPI No. 6 (Zona 6)",
        "PA_Str_1" : "6",
        "PA_Num_1" : 6
      },
      "geometry" : {
        "x" : 123.70678752500008,
        "y" : 6.8512437850000687
      }
    },
    {
      "attributes" : {
        "FID" : 76,
        "FID_viirs_" : -1,
        "PA_Str" : "6",
        "DMSLat" : "06°09'35.57\" LU",
        "DMSLon" : "123°51'51.36\" BT",
        "NAME" : "Titik ZPPI No. 7 (Zona 6)",
        "PA_Str_1" : "6",
        "PA_Num_1" : 6
      },
      "geometry" : {
        "x" : 123.86426875400002,
        "y" : 6.1598818380000111
      }
    },
    {
      "attributes" : {
        "FID" : 77,
        "FID_viirs_" : -1,
        "PA_Str" : "6",
        "DMSLat" : "03°32'06.92\" LU",
        "DMSLon" : "124°01'14.00\" BT",
        "NAME" : "Titik ZPPI No. 8 (Zona 6)",
        "PA_Str_1" : "6",
        "PA_Num_1" : 6
      },
      "geometry" : {
        "x" : 124.02055609900005,
        "y" : 3.5352556900000245
      }
    },
    {
      "attributes" : {
        "FID" : 78,
        "FID_viirs_" : -1,
        "PA_Str" : "6",
        "DMSLat" : "03°31'40.55\" LU",
        "DMSLon" : "124°08'01.74\" BT",
        "NAME" : "Titik ZPPI No. 9 (Zona 6)",
        "PA_Str_1" : "6",
        "PA_Num_1" : 6
      },
      "geometry" : {
        "x" : 124.13381867900009,
        "y" : 3.5279315180000239
      }
    },
    {
      "attributes" : {
        "FID" : 79,
        "FID_viirs_" : -1,
        "PA_Str" : "6",
        "DMSLat" : "03°28'15.55\" LU",
        "DMSLon" : "124°10'40.33\" BT",
        "NAME" : "Titik ZPPI No. 10 (Zona 6)",
        "PA_Str_1" : "6",
        "PA_Num_1" : 6
      },
      "geometry" : {
        "x" : 124.17786977099999,
        "y" : 3.4709888009999936
      }
    },
    {
      "attributes" : {
        "FID" : 80,
        "FID_viirs_" : -1,
        "PA_Str" : "6",
        "DMSLat" : "03°18'25.31\" LU",
        "DMSLon" : "124°24'28.02\" BT",
        "NAME" : "Titik ZPPI No. 11 (Zona 6)",
        "PA_Str_1" : "6",
        "PA_Num_1" : 6
      },
      "geometry" : {
        "x" : 124.40778585500004,
        "y" : 3.3070311460000248
      }
    },
    {
      "attributes" : {
        "FID" : 81,
        "FID_viirs_" : -1,
        "PA_Str" : "6",
        "DMSLat" : "03°53'55.20\" LU",
        "DMSLon" : "124°26'03.04\" BT",
        "NAME" : "Titik ZPPI No. 12 (Zona 6)",
        "PA_Str_1" : "6",
        "PA_Num_1" : 6
      },
      "geometry" : {
        "x" : 124.43418003600007,
        "y" : 3.8986675500000203
      }
    },
    {
      "attributes" : {
        "FID" : 82,
        "FID_viirs_" : -1,
        "PA_Str" : "6",
        "DMSLat" : "04°06'01.65\" LU",
        "DMSLon" : "124°28'56.84\" BT",
        "NAME" : "Titik ZPPI No. 13 (Zona 6)",
        "PA_Str_1" : "6",
        "PA_Num_1" : 6
      },
      "geometry" : {
        "x" : 124.48245560699999,
        "y" : 4.1004603910001016
      }
    },
    {
      "attributes" : {
        "FID" : 83,
        "FID_viirs_" : -1,
        "PA_Str" : "6",
        "DMSLat" : "03°16'35.79\" LU",
        "DMSLon" : "124°33'06.22\" BT",
        "NAME" : "Titik ZPPI No. 14 (Zona 6)",
        "PA_Str_1" : "6",
        "PA_Num_1" : 6
      },
      "geometry" : {
        "x" : 124.5517278300001,
        "y" : 3.276608812000056
      }
    },
    {
      "attributes" : {
        "FID" : 84,
        "FID_viirs_" : -1,
        "PA_Str" : "6",
        "DMSLat" : "04°18'49.07\" LU",
        "DMSLon" : "124°34'15.32\" BT",
        "NAME" : "Titik ZPPI No. 15 (Zona 6)",
        "PA_Str_1" : "6",
        "PA_Num_1" : 6
      },
      "geometry" : {
        "x" : 124.57092262500014,
        "y" : 4.3136310400001179
      }
    },
    {
      "attributes" : {
        "FID" : 85,
        "FID_viirs_" : -1,
        "PA_Str" : "6",
        "DMSLat" : "03°47'22.79\" LU",
        "DMSLon" : "124°35'51.64\" BT",
        "NAME" : "Titik ZPPI No. 16 (Zona 6)",
        "PA_Str_1" : "6",
        "PA_Num_1" : 6
      },
      "geometry" : {
        "x" : 124.59767799500001,
        "y" : 3.7896658820001008
      }
    },
    {
      "attributes" : {
        "FID" : 86,
        "FID_viirs_" : -1,
        "PA_Str" : "6",
        "DMSLat" : "03°41'44.21\" LU",
        "DMSLon" : "124°43'59.00\" BT",
        "NAME" : "Titik ZPPI No. 17 (Zona 6)",
        "PA_Str_1" : "6",
        "PA_Num_1" : 6
      },
      "geometry" : {
        "x" : 124.73305819300006,
        "y" : 3.6956139230000709
      }
    },
    {
      "attributes" : {
        "FID" : 87,
        "FID_viirs_" : -1,
        "PA_Str" : "6",
        "DMSLat" : "03°37'44.69\" LU",
        "DMSLon" : "124°50'53.01\" BT",
        "NAME" : "Titik ZPPI No. 18 (Zona 6)",
        "PA_Str_1" : "6",
        "PA_Num_1" : 6
      },
      "geometry" : {
        "x" : 124.8480608240001,
        "y" : 3.6290826690000912
      }
    },
    {
      "attributes" : {
        "FID" : 88,
        "FID_viirs_" : -1,
        "PA_Str" : "6",
        "DMSLat" : "00°22'05.04\" LU",
        "DMSLon" : "124°52'37.69\" BT",
        "NAME" : "Titik ZPPI No. 19 (Zona 6)",
        "PA_Str_1" : "6",
        "PA_Num_1" : 6
      },
      "geometry" : {
        "x" : 124.87713808900007,
        "y" : 0.3680668810000256
      }
    },
    {
      "attributes" : {
        "FID" : 89,
        "FID_viirs_" : -1,
        "PA_Str" : "6",
        "DMSLat" : "00°37'02.13\" LU",
        "DMSLon" : "125°10'29.98\" BT",
        "NAME" : "Titik ZPPI No. 20 (Zona 6)",
        "PA_Str_1" : "6",
        "PA_Num_1" : 6
      },
      "geometry" : {
        "x" : 125.17499684000011,
        "y" : 0.61726090700008029
      }
    },
    {
      "attributes" : {
        "FID" : 90,
        "FID_viirs_" : -1,
        "PA_Str" : "6",
        "DMSLat" : "00°42'12.49\" LU",
        "DMSLon" : "125°10'46.74\" BT",
        "NAME" : "Titik ZPPI No. 21 (Zona 6)",
        "PA_Str_1" : "6",
        "PA_Num_1" : 6
      },
      "geometry" : {
        "x" : 125.17965273300004,
        "y" : 0.70347088400007607
      }
    },
    {
      "attributes" : {
        "FID" : 91,
        "FID_viirs_" : -1,
        "PA_Str" : "6",
        "DMSLat" : "05°05'31.78\" LU",
        "DMSLon" : "125°14'39.20\" BT",
        "NAME" : "Titik ZPPI No. 22 (Zona 6)",
        "PA_Str_1" : "6",
        "PA_Num_1" : 6
      },
      "geometry" : {
        "x" : 125.24422325999998,
        "y" : 5.0921636339999878
      }
    },
    {
      "attributes" : {
        "FID" : 92,
        "FID_viirs_" : -1,
        "PA_Str" : "6",
        "DMSLat" : "05°14'31.28\" LU",
        "DMSLon" : "125°17'36.53\" BT",
        "NAME" : "Titik ZPPI No. 23 (Zona 6)",
        "PA_Str_1" : "6",
        "PA_Num_1" : 6
      },
      "geometry" : {
        "x" : 125.29348131500002,
        "y" : 5.2420242540000963
      }
    },
    {
      "attributes" : {
        "FID" : 93,
        "FID_viirs_" : -1,
        "PA_Str" : "6",
        "DMSLat" : "00°41'20.95\" LU",
        "DMSLon" : "125°19'07.42\" BT",
        "NAME" : "Titik ZPPI No. 24 (Zona 6)",
        "PA_Str_1" : "6",
        "PA_Num_1" : 6
      },
      "geometry" : {
        "x" : 125.31872829500006,
        "y" : 0.68915324100008135
      }
    },
    {
      "attributes" : {
        "FID" : 94,
        "FID_viirs_" : -1,
        "PA_Str" : "6",
        "DMSLat" : "00°45'40.61\" LU",
        "DMSLon" : "125°23'50.39\" BT",
        "NAME" : "Titik ZPPI No. 25 (Zona 6)",
        "PA_Str_1" : "6",
        "PA_Num_1" : 6
      },
      "geometry" : {
        "x" : 125.39733217,
        "y" : 0.76128154000006631
      }
    },
    {
      "attributes" : {
        "FID" : 95,
        "FID_viirs_" : -1,
        "PA_Str" : "6",
        "DMSLat" : "05°06'48.65\" LU",
        "DMSLon" : "125°26'05.10\" BT",
        "NAME" : "Titik ZPPI No. 26 (Zona 6)",
        "PA_Str_1" : "6",
        "PA_Num_1" : 6
      },
      "geometry" : {
        "x" : 125.43475070400009,
        "y" : 5.1135141920000429
      }
    },
    {
      "attributes" : {
        "FID" : 96,
        "FID_viirs_" : -1,
        "PA_Str" : "6",
        "DMSLat" : "00°42'32.40\" LU",
        "DMSLon" : "125°26'24.20\" BT",
        "NAME" : "Titik ZPPI No. 27 (Zona 6)",
        "PA_Str_1" : "6",
        "PA_Num_1" : 6
      },
      "geometry" : {
        "x" : 125.44005636800014,
        "y" : 0.70900005400006094
      }
    },
    {
      "attributes" : {
        "FID" : 97,
        "FID_viirs_" : -1,
        "PA_Str" : "6",
        "DMSLat" : "05°04'22.84\" LU",
        "DMSLon" : "125°28'18.91\" BT",
        "NAME" : "Titik ZPPI No. 28 (Zona 6)",
        "PA_Str_1" : "6",
        "PA_Num_1" : 6
      },
      "geometry" : {
        "x" : 125.47192014900011,
        "y" : 5.0730123630000037
      }
    },
    {
      "attributes" : {
        "FID" : 98,
        "FID_viirs_" : -1,
        "PA_Str" : "6",
        "DMSLat" : "05°08'27.77\" LU",
        "DMSLon" : "125°30'00.64\" BT",
        "NAME" : "Titik ZPPI No. 29 (Zona 6)",
        "PA_Str_1" : "6",
        "PA_Num_1" : 6
      },
      "geometry" : {
        "x" : 125.50017945800008,
        "y" : 5.1410493390000447
      }
    },
    {
      "attributes" : {
        "FID" : 99,
        "FID_viirs_" : -1,
        "PA_Str" : "6",
        "DMSLat" : "00°37'16.79\" LU",
        "DMSLon" : "125°33'34.29\" BT",
        "NAME" : "Titik ZPPI No. 30 (Zona 6)",
        "PA_Str_1" : "6",
        "PA_Num_1" : 6
      },
      "geometry" : {
        "x" : 125.559527644,
        "y" : 0.62133249400007884
      }
    },
    {
      "attributes" : {
        "FID" : 100,
        "FID_viirs_" : -1,
        "PA_Str" : "6",
        "DMSLat" : "00°43'32.69\" LU",
        "DMSLon" : "125°34'01.44\" BT",
        "NAME" : "Titik ZPPI No. 31 (Zona 6)",
        "PA_Str_1" : "6",
        "PA_Num_1" : 6
      },
      "geometry" : {
        "x" : 125.56706889200011,
        "y" : 0.72574780000003969
      }
    },
    {
      "attributes" : {
        "FID" : 101,
        "FID_viirs_" : -1,
        "PA_Str" : "6",
        "DMSLat" : "04°51'36.92\" LU",
        "DMSLon" : "125°35'25.67\" BT",
        "NAME" : "Titik ZPPI No. 32 (Zona 6)",
        "PA_Str_1" : "6",
        "PA_Num_1" : 6
      },
      "geometry" : {
        "x" : 125.59046493200003,
        "y" : 4.8602575520000215
      }
    },
    {
      "attributes" : {
        "FID" : 102,
        "FID_viirs_" : -1,
        "PA_Str" : "6",
        "DMSLat" : "02°30'55.70\" LU",
        "DMSLon" : "125°43'05.16\" BT",
        "NAME" : "Titik ZPPI No. 33 (Zona 6)",
        "PA_Str_1" : "6",
        "PA_Num_1" : 6
      },
      "geometry" : {
        "x" : 125.71810011400009,
        "y" : 2.5154729450000382
      }
    },
    {
      "attributes" : {
        "FID" : 103,
        "FID_viirs_" : -1,
        "PA_Str" : "6",
        "DMSLat" : "02°37'38.72\" LU",
        "DMSLon" : "125°46'44.09\" BT",
        "NAME" : "Titik ZPPI No. 34 (Zona 6)",
        "PA_Str_1" : "6",
        "PA_Num_1" : 6
      },
      "geometry" : {
        "x" : 125.7789156250001,
        "y" : 2.6274232550000356
      }
    }
  ]
}