{
  "displayFieldName" : "",
  "fieldAliases" : {
    "FID" : "FID",
    "FID_viirs_" : "FID_viirs_",
    "PA_Str" : "PA_Str",
    "DMSLat" : "DMSLat",
    "DMSLon" : "DMSLon",
    "NAME" : "NAME",
    "PA_Str_1" : "PA_Str_1",
    "PA_Num_1" : "PA_Num_1"
  },
  "geometryType" : "esriGeometryPoint",
  "spatialReference" : {
    "wkid" : 4326,
    "latestWkid" : 4326
  },
  "fields" : [
    {
      "name" : "FID",
      "type" : "esriFieldTypeOID",
      "alias" : "FID"
    },
    {
      "name" : "FID_viirs_",
      "type" : "esriFieldTypeInteger",
      "alias" : "FID_viirs_"
    },
    {
      "name" : "PA_Str",
      "type" : "esriFieldTypeString",
      "alias" : "PA_Str",
      "length" : 3
    },
    {
      "name" : "DMSLat",
      "type" : "esriFieldTypeString",
      "alias" : "DMSLat",
      "length" : 254
    },
    {
      "name" : "DMSLon",
      "type" : "esriFieldTypeString",
      "alias" : "DMSLon",
      "length" : 254
    },
    {
      "name" : "NAME",
      "type" : "esriFieldTypeString",
      "alias" : "NAME",
      "length" : 50
    },
    {
      "name" : "PA_Str_1",
      "type" : "esriFieldTypeString",
      "alias" : "PA_Str_1",
      "length" : 3
    },
    {
      "name" : "PA_Num_1",
      "type" : "esriFieldTypeSmallInteger",
      "alias" : "PA_Num_1"
    }
  ],
  "features" : [
    {
      "attributes" : {
        "FID" : 32,
        "FID_viirs_" : -1,
        "PA_Str" : "6",
        "DMSLat" : "01°36'19.64\" LU",
        "DMSLon" : "122°00'03.99\" BT",
        "NAME" : "Titik ZPPI No. 1 (Zona 6)",
        "PA_Str_1" : "6",
        "PA_Num_1" : 6
      },
      "geometry" : {
        "x" : 122.00110901800005,
        "y" : 1.6054582380000539
      }
    },
    {
      "attributes" : {
        "FID" : 33,
        "FID_viirs_" : -1,
        "PA_Str" : "6",
        "DMSLat" : "02°32'53.40\" LU",
        "DMSLon" : "122°13'48.98\" BT",
        "NAME" : "Titik ZPPI No. 2 (Zona 6)",
        "PA_Str_1" : "6",
        "PA_Num_1" : 6
      },
      "geometry" : {
        "x" : 122.2302723490001,
        "y" : 2.5481667410000099
      }
    },
    {
      "attributes" : {
        "FID" : 34,
        "FID_viirs_" : -1,
        "PA_Str" : "6",
        "DMSLat" : "02°31'27.29\" LU",
        "DMSLon" : "122°20'40.12\" BT",
        "NAME" : "Titik ZPPI No. 3 (Zona 6)",
        "PA_Str_1" : "6",
        "PA_Num_1" : 6
      },
      "geometry" : {
        "x" : 122.34447979000007,
        "y" : 2.5242487020000617
      }
    },
    {
      "attributes" : {
        "FID" : 35,
        "FID_viirs_" : -1,
        "PA_Str" : "6",
        "DMSLat" : "02°14'36.10\" LU",
        "DMSLon" : "122°28'29.16\" BT",
        "NAME" : "Titik ZPPI No. 4 (Zona 6)",
        "PA_Str_1" : "6",
        "PA_Num_1" : 6
      },
      "geometry" : {
        "x" : 122.47476770900005,
        "y" : 2.2433638310000639
      }
    },
    {
      "attributes" : {
        "FID" : 36,
        "FID_viirs_" : -1,
        "PA_Str" : "6",
        "DMSLat" : "02°26'52.46\" LU",
        "DMSLon" : "122°29'39.78\" BT",
        "NAME" : "Titik ZPPI No. 5 (Zona 6)",
        "PA_Str_1" : "6",
        "PA_Num_1" : 6
      },
      "geometry" : {
        "x" : 122.49438488300004,
        "y" : 2.4479063070000109
      }
    },
    {
      "attributes" : {
        "FID" : 37,
        "FID_viirs_" : -1,
        "PA_Str" : "6",
        "DMSLat" : "01°32'31.51\" LU",
        "DMSLon" : "122°33'52.96\" BT",
        "NAME" : "Titik ZPPI No. 6 (Zona 6)",
        "PA_Str_1" : "6",
        "PA_Num_1" : 6
      },
      "geometry" : {
        "x" : 122.564713813,
        "y" : 1.5420866370001143
      }
    },
    {
      "attributes" : {
        "FID" : 38,
        "FID_viirs_" : -1,
        "PA_Str" : "6",
        "DMSLat" : "02°28'12.02\" LU",
        "DMSLon" : "122°34'10.68\" BT",
        "NAME" : "Titik ZPPI No. 7 (Zona 6)",
        "PA_Str_1" : "6",
        "PA_Num_1" : 6
      },
      "geometry" : {
        "x" : 122.56963422100016,
        "y" : 2.4700058430000418
      }
    },
    {
      "attributes" : {
        "FID" : 39,
        "FID_viirs_" : -1,
        "PA_Str" : "6",
        "DMSLat" : "02°31'25.67\" LU",
        "DMSLon" : "122°34'14.33\" BT",
        "NAME" : "Titik ZPPI No. 8 (Zona 6)",
        "PA_Str_1" : "6",
        "PA_Num_1" : 6
      },
      "geometry" : {
        "x" : 122.57064725400005,
        "y" : 2.523797505000033
      }
    },
    {
      "attributes" : {
        "FID" : 40,
        "FID_viirs_" : -1,
        "PA_Str" : "6",
        "DMSLat" : "01°35'31.94\" LU",
        "DMSLon" : "122°35'51.96\" BT",
        "NAME" : "Titik ZPPI No. 9 (Zona 6)",
        "PA_Str_1" : "6",
        "PA_Num_1" : 6
      },
      "geometry" : {
        "x" : 122.59776791500012,
        "y" : 1.5922069670000063
      }
    },
    {
      "attributes" : {
        "FID" : 41,
        "FID_viirs_" : -1,
        "PA_Str" : "6",
        "DMSLat" : "02°14'21.27\" LU",
        "DMSLon" : "122°38'14.14\" BT",
        "NAME" : "Titik ZPPI No. 10 (Zona 6)",
        "PA_Str_1" : "6",
        "PA_Num_1" : 6
      },
      "geometry" : {
        "x" : 122.63726317700001,
        "y" : 2.2392431359999989
      }
    },
    {
      "attributes" : {
        "FID" : 42,
        "FID_viirs_" : -1,
        "PA_Str" : "6",
        "DMSLat" : "01°37'11.35\" LU",
        "DMSLon" : "122°43'50.54\" BT",
        "NAME" : "Titik ZPPI No. 11 (Zona 6)",
        "PA_Str_1" : "6",
        "PA_Num_1" : 6
      },
      "geometry" : {
        "x" : 122.73070618600002,
        "y" : 1.6198205940000179
      }
    },
    {
      "attributes" : {
        "FID" : 43,
        "FID_viirs_" : -1,
        "PA_Str" : "6",
        "DMSLat" : "01°05'47.07\" LU",
        "DMSLon" : "123°00'22.87\" BT",
        "NAME" : "Titik ZPPI No. 12 (Zona 6)",
        "PA_Str_1" : "6",
        "PA_Num_1" : 6
      },
      "geometry" : {
        "x" : 123.00635487000011,
        "y" : 1.0964086510000328
      }
    },
    {
      "attributes" : {
        "FID" : 44,
        "FID_viirs_" : -1,
        "PA_Str" : "6",
        "DMSLat" : "03°09'29.28\" LU",
        "DMSLon" : "123°08'50.46\" BT",
        "NAME" : "Titik ZPPI No. 13 (Zona 6)",
        "PA_Str_1" : "6",
        "PA_Num_1" : 6
      },
      "geometry" : {
        "x" : 123.14735020500007,
        "y" : 3.1581335000001012
      }
    },
    {
      "attributes" : {
        "FID" : 45,
        "FID_viirs_" : -1,
        "PA_Str" : "6",
        "DMSLat" : "01°11'31.93\" LU",
        "DMSLon" : "123°09'26.35\" BT",
        "NAME" : "Titik ZPPI No. 14 (Zona 6)",
        "PA_Str_1" : "6",
        "PA_Num_1" : 6
      },
      "geometry" : {
        "x" : 123.15732135000006,
        "y" : 1.1922050519999807
      }
    },
    {
      "attributes" : {
        "FID" : 46,
        "FID_viirs_" : -1,
        "PA_Str" : "6",
        "DMSLat" : "03°05'07.41\" LU",
        "DMSLon" : "123°16'28.03\" BT",
        "NAME" : "Titik ZPPI No. 15 (Zona 6)",
        "PA_Str_1" : "6",
        "PA_Num_1" : 6
      },
      "geometry" : {
        "x" : 123.27445369400002,
        "y" : 3.0853943710000244
      }
    },
    {
      "attributes" : {
        "FID" : 47,
        "FID_viirs_" : -1,
        "PA_Str" : "6",
        "DMSLat" : "01°09'56.41\" LU",
        "DMSLon" : "123°20'23.02\" BT",
        "NAME" : "Titik ZPPI No. 16 (Zona 6)",
        "PA_Str_1" : "6",
        "PA_Num_1" : 6
      },
      "geometry" : {
        "x" : 123.33973044200002,
        "y" : 1.1656696860001006
      }
    },
    {
      "attributes" : {
        "FID" : 48,
        "FID_viirs_" : -1,
        "PA_Str" : "6",
        "DMSLat" : "03°00'00.31\" LU",
        "DMSLon" : "123°23'59.65\" BT",
        "NAME" : "Titik ZPPI No. 17 (Zona 6)",
        "PA_Str_1" : "6",
        "PA_Num_1" : 6
      },
      "geometry" : {
        "x" : 123.39990280200001,
        "y" : 3.0000877829999908
      }
    },
    {
      "attributes" : {
        "FID" : 49,
        "FID_viirs_" : -1,
        "PA_Str" : "6",
        "DMSLat" : "01°08'48.28\" LU",
        "DMSLon" : "123°30'09.89\" BT",
        "NAME" : "Titik ZPPI No. 18 (Zona 6)",
        "PA_Str_1" : "6",
        "PA_Num_1" : 6
      },
      "geometry" : {
        "x" : 123.50274939500002,
        "y" : 1.1467456940000922
      }
    },
    {
      "attributes" : {
        "FID" : 50,
        "FID_viirs_" : -1,
        "PA_Str" : "6",
        "DMSLat" : "05°36'47.02\" LU",
        "DMSLon" : "123°42'47.56\" BT",
        "NAME" : "Titik ZPPI No. 19 (Zona 6)",
        "PA_Str_1" : "6",
        "PA_Num_1" : 6
      },
      "geometry" : {
        "x" : 123.71321343900001,
        "y" : 5.6130637600000668
      }
    },
    {
      "attributes" : {
        "FID" : 51,
        "FID_viirs_" : -1,
        "PA_Str" : "6",
        "DMSLat" : "01°07'35.72\" LU",
        "DMSLon" : "123°43'06.15\" BT",
        "NAME" : "Titik ZPPI No. 20 (Zona 6)",
        "PA_Str_1" : "6",
        "PA_Num_1" : 6
      },
      "geometry" : {
        "x" : 123.71837586300003,
        "y" : 1.1265894610000018
      }
    },
    {
      "attributes" : {
        "FID" : 52,
        "FID_viirs_" : -1,
        "PA_Str" : "6",
        "DMSLat" : "04°14'26.64\" LU",
        "DMSLon" : "123°47'12.48\" BT",
        "NAME" : "Titik ZPPI No. 21 (Zona 6)",
        "PA_Str_1" : "6",
        "PA_Num_1" : 6
      },
      "geometry" : {
        "x" : 123.78680274400008,
        "y" : 4.2407334030000712
      }
    },
    {
      "attributes" : {
        "FID" : 53,
        "FID_viirs_" : -1,
        "PA_Str" : "6",
        "DMSLat" : "04°28'29.55\" LU",
        "DMSLon" : "123°51'18.09\" BT",
        "NAME" : "Titik ZPPI No. 22 (Zona 6)",
        "PA_Str_1" : "6",
        "PA_Num_1" : 6
      },
      "geometry" : {
        "x" : 123.85502683199998,
        "y" : 4.4748768840000643
      }
    },
    {
      "attributes" : {
        "FID" : 54,
        "FID_viirs_" : -1,
        "PA_Str" : "6",
        "DMSLat" : "01°00'59.49\" LU",
        "DMSLon" : "123°51'54.40\" BT",
        "NAME" : "Titik ZPPI No. 23 (Zona 6)",
        "PA_Str_1" : "6",
        "PA_Num_1" : 6
      },
      "geometry" : {
        "x" : 123.86511127200001,
        "y" : 1.0165264190001047
      }
    },
    {
      "attributes" : {
        "FID" : 55,
        "FID_viirs_" : -1,
        "PA_Str" : "6",
        "DMSLat" : "04°23'43.05\" LU",
        "DMSLon" : "123°56'39.69\" BT",
        "NAME" : "Titik ZPPI No. 24 (Zona 6)",
        "PA_Str_1" : "6",
        "PA_Num_1" : 6
      },
      "geometry" : {
        "x" : 123.94436062300008,
        "y" : 4.3952921300000583
      }
    },
    {
      "attributes" : {
        "FID" : 56,
        "FID_viirs_" : -1,
        "PA_Str" : "6",
        "DMSLat" : "04°31'38.76\" LU",
        "DMSLon" : "123°58'35.29\" BT",
        "NAME" : "Titik ZPPI No. 25 (Zona 6)",
        "PA_Str_1" : "6",
        "PA_Num_1" : 6
      },
      "geometry" : {
        "x" : 123.97647064400006,
        "y" : 4.5274353510000722
      }
    },
    {
      "attributes" : {
        "FID" : 57,
        "FID_viirs_" : -1,
        "PA_Str" : "6",
        "DMSLat" : "04°20'42.78\" LU",
        "DMSLon" : "123°59'59.87\" BT",
        "NAME" : "Titik ZPPI No. 26 (Zona 6)",
        "PA_Str_1" : "6",
        "PA_Num_1" : 6
      },
      "geometry" : {
        "x" : 123.99996484700011,
        "y" : 4.3452186120000427
      }
    },
    {
      "attributes" : {
        "FID" : 58,
        "FID_viirs_" : -1,
        "PA_Str" : "6",
        "DMSLat" : "04°29'59.78\" LU",
        "DMSLon" : "124°00'44.93\" BT",
        "NAME" : "Titik ZPPI No. 27 (Zona 6)",
        "PA_Str_1" : "6",
        "PA_Num_1" : 6
      },
      "geometry" : {
        "x" : 124.01248157200004,
        "y" : 4.4999389529999902
      }
    },
    {
      "attributes" : {
        "FID" : 59,
        "FID_viirs_" : -1,
        "PA_Str" : "6",
        "DMSLat" : "04°34'35.13\" LU",
        "DMSLon" : "124°07'22.71\" BT",
        "NAME" : "Titik ZPPI No. 28 (Zona 6)",
        "PA_Str_1" : "6",
        "PA_Num_1" : 6
      },
      "geometry" : {
        "x" : 124.12297753000006,
        "y" : 4.5764275480000585
      }
    },
    {
      "attributes" : {
        "FID" : 60,
        "FID_viirs_" : -1,
        "PA_Str" : "6",
        "DMSLat" : "04°43'35.69\" LU",
        "DMSLon" : "124°14'04.54\" BT",
        "NAME" : "Titik ZPPI No. 29 (Zona 6)",
        "PA_Str_1" : "6",
        "PA_Num_1" : 6
      },
      "geometry" : {
        "x" : 124.2345945640001,
        "y" : 4.7265807190000366
      }
    },
    {
      "attributes" : {
        "FID" : 61,
        "FID_viirs_" : -1,
        "PA_Str" : "6",
        "DMSLat" : "01°19'49.01\" LU",
        "DMSLon" : "124°15'31.97\" BT",
        "NAME" : "Titik ZPPI No. 30 (Zona 6)",
        "PA_Str_1" : "6",
        "PA_Num_1" : 6
      },
      "geometry" : {
        "x" : 124.25888322800007,
        "y" : 1.3302833259999893
      }
    },
    {
      "attributes" : {
        "FID" : 62,
        "FID_viirs_" : -1,
        "PA_Str" : "6",
        "DMSLat" : "01°26'07.64\" LU",
        "DMSLon" : "124°18'49.42\" BT",
        "NAME" : "Titik ZPPI No. 31 (Zona 6)",
        "PA_Str_1" : "6",
        "PA_Num_1" : 6
      },
      "geometry" : {
        "x" : 124.31373026800009,
        "y" : 1.4354567720000624
      }
    },
    {
      "attributes" : {
        "FID" : 63,
        "FID_viirs_" : -1,
        "PA_Str" : "6",
        "DMSLat" : "04°42'47.38\" LU",
        "DMSLon" : "124°21'02.62\" BT",
        "NAME" : "Titik ZPPI No. 32 (Zona 6)",
        "PA_Str_1" : "6",
        "PA_Num_1" : 6
      },
      "geometry" : {
        "x" : 124.35072834800012,
        "y" : 4.7131618070000627
      }
    },
    {
      "attributes" : {
        "FID" : 64,
        "FID_viirs_" : -1,
        "PA_Str" : "6",
        "DMSLat" : "04°46'53.78\" LU",
        "DMSLon" : "124°22'06.06\" BT",
        "NAME" : "Titik ZPPI No. 33 (Zona 6)",
        "PA_Str_1" : "6",
        "PA_Num_1" : 6
      },
      "geometry" : {
        "x" : 124.36835259400004,
        "y" : 4.7816079640000311
      }
    },
    {
      "attributes" : {
        "FID" : 65,
        "FID_viirs_" : -1,
        "PA_Str" : "6",
        "DMSLat" : "04°52'03.40\" LU",
        "DMSLon" : "124°30'54.73\" BT",
        "NAME" : "Titik ZPPI No. 34 (Zona 6)",
        "PA_Str_1" : "6",
        "PA_Num_1" : 6
      },
      "geometry" : {
        "x" : 124.51520426600007,
        "y" : 4.8676115110000886
      }
    },
    {
      "attributes" : {
        "FID" : 66,
        "FID_viirs_" : -1,
        "PA_Str" : "6",
        "DMSLat" : "04°56'09.47\" LU",
        "DMSLon" : "124°33'04.24\" BT",
        "NAME" : "Titik ZPPI No. 35 (Zona 6)",
        "PA_Str_1" : "6",
        "PA_Num_1" : 6
      },
      "geometry" : {
        "x" : 124.55118030400001,
        "y" : 4.9359663980000548
      }
    },
    {
      "attributes" : {
        "FID" : 67,
        "FID_viirs_" : -1,
        "PA_Str" : "6",
        "DMSLat" : "00°01'22.66\" LU",
        "DMSLon" : "124°33'15.00\" BT",
        "NAME" : "Titik ZPPI No. 36 (Zona 6)",
        "PA_Str_1" : "6",
        "PA_Num_1" : 6
      },
      "geometry" : {
        "x" : 124.55416818800005,
        "y" : 0.022961783000038594
      }
    },
    {
      "attributes" : {
        "FID" : 68,
        "FID_viirs_" : -1,
        "PA_Str" : "6",
        "DMSLat" : "00°08'30.73\" LU",
        "DMSLon" : "124°39'41.56\" BT",
        "NAME" : "Titik ZPPI No. 37 (Zona 6)",
        "PA_Str_1" : "6",
        "PA_Num_1" : 6
      },
      "geometry" : {
        "x" : 124.66154653400012,
        "y" : 0.14187005400002306
      }
    },
    {
      "attributes" : {
        "FID" : 69,
        "FID_viirs_" : -1,
        "PA_Str" : "6",
        "DMSLat" : "04°57'41.04\" LU",
        "DMSLon" : "125°04'18.66\" BT",
        "NAME" : "Titik ZPPI No. 38 (Zona 6)",
        "PA_Str_1" : "6",
        "PA_Num_1" : 6
      },
      "geometry" : {
        "x" : 125.0718519620001,
        "y" : 4.9614017030000426
      }
    },
    {
      "attributes" : {
        "FID" : 70,
        "FID_viirs_" : -1,
        "PA_Str" : "6",
        "DMSLat" : "05°02'18.45\" LU",
        "DMSLon" : "125°04'26.59\" BT",
        "NAME" : "Titik ZPPI No. 39 (Zona 6)",
        "PA_Str_1" : "6",
        "PA_Num_1" : 6
      },
      "geometry" : {
        "x" : 125.07405370100003,
        "y" : 5.0384597100000619
      }
    },
    {
      "attributes" : {
        "FID" : 71,
        "FID_viirs_" : -1,
        "PA_Str" : "6",
        "DMSLat" : "05°00'24.37\" LU",
        "DMSLon" : "125°09'22.75\" BT",
        "NAME" : "Titik ZPPI No. 40 (Zona 6)",
        "PA_Str_1" : "6",
        "PA_Num_1" : 6
      },
      "geometry" : {
        "x" : 125.15632047800007,
        "y" : 5.0067707090000049
      }
    },
    {
      "attributes" : {
        "FID" : 72,
        "FID_viirs_" : -1,
        "PA_Str" : "6",
        "DMSLat" : "05°05'29.66\" LU",
        "DMSLon" : "125°10'23.86\" BT",
        "NAME" : "Titik ZPPI No. 41 (Zona 6)",
        "PA_Str_1" : "6",
        "PA_Num_1" : 6
      },
      "geometry" : {
        "x" : 125.17329454000003,
        "y" : 5.0915731960000734
      }
    },
    {
      "attributes" : {
        "FID" : 73,
        "FID_viirs_" : -1,
        "PA_Str" : "6",
        "DMSLat" : "04°54'00.44\" LU",
        "DMSLon" : "125°11'45.75\" BT",
        "NAME" : "Titik ZPPI No. 42 (Zona 6)",
        "PA_Str_1" : "6",
        "PA_Num_1" : 6
      },
      "geometry" : {
        "x" : 125.19604213600005,
        "y" : 4.9001249080000555
      }
    },
    {
      "attributes" : {
        "FID" : 74,
        "FID_viirs_" : -1,
        "PA_Str" : "6",
        "DMSLat" : "04°57'15.90\" LU",
        "DMSLon" : "125°18'11.85\" BT",
        "NAME" : "Titik ZPPI No. 43 (Zona 6)",
        "PA_Str_1" : "6",
        "PA_Num_1" : 6
      },
      "geometry" : {
        "x" : 125.30329281300013,
        "y" : 4.9544185810000165
      }
    },
    {
      "attributes" : {
        "FID" : 75,
        "FID_viirs_" : -1,
        "PA_Str" : "6",
        "DMSLat" : "05°04'37.55\" LU",
        "DMSLon" : "125°27'03.29\" BT",
        "NAME" : "Titik ZPPI No. 44 (Zona 6)",
        "PA_Str_1" : "6",
        "PA_Num_1" : 6
      },
      "geometry" : {
        "x" : 125.45091429500006,
        "y" : 5.077099991000086
      }
    },
    {
      "attributes" : {
        "FID" : 76,
        "FID_viirs_" : -1,
        "PA_Str" : "6",
        "DMSLat" : "05°15'50.24\" LU",
        "DMSLon" : "125°28'34.31\" BT",
        "NAME" : "Titik ZPPI No. 45 (Zona 6)",
        "PA_Str_1" : "6",
        "PA_Num_1" : 6
      },
      "geometry" : {
        "x" : 125.47619860400007,
        "y" : 5.2639565210000541
      }
    },
    {
      "attributes" : {
        "FID" : 77,
        "FID_viirs_" : -1,
        "PA_Str" : "6",
        "DMSLat" : "05°12'41.03\" LU",
        "DMSLon" : "125°29'44.04\" BT",
        "NAME" : "Titik ZPPI No. 46 (Zona 6)",
        "PA_Str_1" : "6",
        "PA_Num_1" : 6
      },
      "geometry" : {
        "x" : 125.49556753600004,
        "y" : 5.2113998860000201
      }
    },
    {
      "attributes" : {
        "FID" : 78,
        "FID_viirs_" : -1,
        "PA_Str" : "6",
        "DMSLat" : "05°06'37.49\" LU",
        "DMSLon" : "125°33'17.32\" BT",
        "NAME" : "Titik ZPPI No. 47 (Zona 6)",
        "PA_Str_1" : "6",
        "PA_Num_1" : 6
      },
      "geometry" : {
        "x" : 125.55481324700011,
        "y" : 5.1104142970000623
      }
    },
    {
      "attributes" : {
        "FID" : 79,
        "FID_viirs_" : -1,
        "PA_Str" : "6",
        "DMSLat" : "06°41'33.84\" LU",
        "DMSLon" : "125°41'00.91\" BT",
        "NAME" : "Titik ZPPI No. 48 (Zona 6)",
        "PA_Str_1" : "6",
        "PA_Num_1" : 6
      },
      "geometry" : {
        "x" : 125.683587609,
        "y" : 6.6927346200000706
      }
    },
    {
      "attributes" : {
        "FID" : 80,
        "FID_viirs_" : -1,
        "PA_Str" : "6",
        "DMSLat" : "06°28'36.98\" LU",
        "DMSLon" : "125°47'37.78\" BT",
        "NAME" : "Titik ZPPI No. 49 (Zona 6)",
        "PA_Str_1" : "6",
        "PA_Num_1" : 6
      },
      "geometry" : {
        "x" : 125.793830036,
        "y" : 6.476939038000026
      }
    },
    {
      "attributes" : {
        "FID" : 81,
        "FID_viirs_" : -1,
        "PA_Str" : "6",
        "DMSLat" : "04°22'09.77\" LU",
        "DMSLon" : "126°10'37.11\" BT",
        "NAME" : "Titik ZPPI No. 50 (Zona 6)",
        "PA_Str_1" : "6",
        "PA_Num_1" : 6
      },
      "geometry" : {
        "x" : 126.17697678100004,
        "y" : 4.369382003000041
      }
    }
  ]
}