{
  "displayFieldName" : "",
  "fieldAliases" : {
    "FID" : "FID",
    "FID_AQUA_2" : "FID_AQUA_2",
    "PA_Str" : "PA_Str",
    "DMSLat" : "DMSLat",
    "DMSLon" : "DMSLon",
    "NAME" : "NAME",
    "PA_Str_1" : "PA_Str_1",
    "PA_Num_1" : "PA_Num_1"
  },
  "geometryType" : "esriGeometryPoint",
  "spatialReference" : {
    "wkid" : 4326,
    "latestWkid" : 4326
  },
  "fields" : [
    {
      "name" : "FID",
      "type" : "esriFieldTypeOID",
      "alias" : "FID"
    },
    {
      "name" : "FID_AQUA_2",
      "type" : "esriFieldTypeInteger",
      "alias" : "FID_AQUA_2"
    },
    {
      "name" : "PA_Str",
      "type" : "esriFieldTypeString",
      "alias" : "PA_Str",
      "length" : 3
    },
    {
      "name" : "DMSLat",
      "type" : "esriFieldTypeString",
      "alias" : "DMSLat",
      "length" : 254
    },
    {
      "name" : "DMSLon",
      "type" : "esriFieldTypeString",
      "alias" : "DMSLon",
      "length" : 254
    },
    {
      "name" : "NAME",
      "type" : "esriFieldTypeString",
      "alias" : "NAME",
      "length" : 50
    },
    {
      "name" : "PA_Str_1",
      "type" : "esriFieldTypeString",
      "alias" : "PA_Str_1",
      "length" : 3
    },
    {
      "name" : "PA_Num_1",
      "type" : "esriFieldTypeSmallInteger",
      "alias" : "PA_Num_1"
    }
  ],
  "features" : [
    {
      "attributes" : {
        "FID" : 11,
        "FID_AQUA_2" : -1,
        "PA_Str" : "6",
        "DMSLat" : "03°51'19.65\" LU",
        "DMSLon" : "122°08'37.64\" BT",
        "NAME" : "Titik ZPPI No. 1 (Zona 6)",
        "PA_Str_1" : "6",
        "PA_Num_1" : 6
      },
      "geometry" : {
        "x" : 122.14379149100007,
        "y" : 3.8554584530000682
      }
    },
    {
      "attributes" : {
        "FID" : 12,
        "FID_AQUA_2" : -1,
        "PA_Str" : "6",
        "DMSLat" : "00°19'10.14\" LU",
        "DMSLon" : "122°13'33.22\" BT",
        "NAME" : "Titik ZPPI No. 2 (Zona 6)",
        "PA_Str_1" : "6",
        "PA_Num_1" : 6
      },
      "geometry" : {
        "x" : 122.22589558299998,
        "y" : 0.31948541000000574
      }
    },
    {
      "attributes" : {
        "FID" : 13,
        "FID_AQUA_2" : -1,
        "PA_Str" : "6",
        "DMSLat" : "00°13'36.94\" LU",
        "DMSLon" : "122°20'57.02\" BT",
        "NAME" : "Titik ZPPI No. 3 (Zona 6)",
        "PA_Str_1" : "6",
        "PA_Num_1" : 6
      },
      "geometry" : {
        "x" : 122.34917455500012,
        "y" : 0.22693016100000207
      }
    },
    {
      "attributes" : {
        "FID" : 14,
        "FID_AQUA_2" : -1,
        "PA_Str" : "6",
        "DMSLat" : "00°06'32.37\" LU",
        "DMSLon" : "122°59'05.37\" BT",
        "NAME" : "Titik ZPPI No. 4 (Zona 6)",
        "PA_Str_1" : "6",
        "PA_Num_1" : 6
      },
      "geometry" : {
        "x" : 122.98482588300013,
        "y" : 0.10899216600009609
      }
    },
    {
      "attributes" : {
        "FID" : 15,
        "FID_AQUA_2" : -1,
        "PA_Str" : "6",
        "DMSLat" : "00°01'34.37\" LU",
        "DMSLon" : "123°09'41.46\" BT",
        "NAME" : "Titik ZPPI No. 5 (Zona 6)",
        "PA_Str_1" : "6",
        "PA_Num_1" : 6
      },
      "geometry" : {
        "x" : 123.16151808200001,
        "y" : 0.026214153000111651
      }
    },
    {
      "attributes" : {
        "FID" : 16,
        "FID_AQUA_2" : -1,
        "PA_Str" : "6",
        "DMSLat" : "00°03'46.28\" LU",
        "DMSLon" : "123°33'29.47\" BT",
        "NAME" : "Titik ZPPI No. 6 (Zona 6)",
        "PA_Str_1" : "6",
        "PA_Num_1" : 6
      },
      "geometry" : {
        "x" : 123.55818769800011,
        "y" : 0.062857245000000006
      }
    },
    {
      "attributes" : {
        "FID" : 17,
        "FID_AQUA_2" : -1,
        "PA_Str" : "6",
        "DMSLat" : "00°04'37.23\" LU",
        "DMSLon" : "123°42'02.08\" BT",
        "NAME" : "Titik ZPPI No. 7 (Zona 6)",
        "PA_Str_1" : "6",
        "PA_Num_1" : 6
      },
      "geometry" : {
        "x" : 123.70058045100005,
        "y" : 0.077010271000052199
      }
    },
    {
      "attributes" : {
        "FID" : 18,
        "FID_AQUA_2" : -1,
        "PA_Str" : "6",
        "DMSLat" : "00°07'42.12\" LU",
        "DMSLon" : "123°52'45.08\" BT",
        "NAME" : "Titik ZPPI No. 8 (Zona 6)",
        "PA_Str_1" : "6",
        "PA_Num_1" : 6
      },
      "geometry" : {
        "x" : 123.87918934700008,
        "y" : 0.12836680200008743
      }
    },
    {
      "attributes" : {
        "FID" : 19,
        "FID_AQUA_2" : -1,
        "PA_Str" : "6",
        "DMSLat" : "00°39'44.84\" LU",
        "DMSLon" : "124°59'09.27\" BT",
        "NAME" : "Titik ZPPI No. 9 (Zona 6)",
        "PA_Str_1" : "6",
        "PA_Num_1" : 6
      },
      "geometry" : {
        "x" : 124.98590860400006,
        "y" : 0.66245802600003145
      }
    },
    {
      "attributes" : {
        "FID" : 20,
        "FID_AQUA_2" : -1,
        "PA_Str" : "6",
        "DMSLat" : "00°37'13.90\" LU",
        "DMSLon" : "125°07'35.71\" BT",
        "NAME" : "Titik ZPPI No. 10 (Zona 6)",
        "PA_Str_1" : "6",
        "PA_Num_1" : 6
      },
      "geometry" : {
        "x" : 125.12658872500003,
        "y" : 0.62052827600006211
      }
    },
    {
      "attributes" : {
        "FID" : 21,
        "FID_AQUA_2" : -1,
        "PA_Str" : "6",
        "DMSLat" : "00°43'33.41\" LU",
        "DMSLon" : "125°08'20.84\" BT",
        "NAME" : "Titik ZPPI No. 11 (Zona 6)",
        "PA_Str_1" : "6",
        "PA_Num_1" : 6
      },
      "geometry" : {
        "x" : 125.13912474399997,
        "y" : 0.72594929900001404
      }
    },
    {
      "attributes" : {
        "FID" : 22,
        "FID_AQUA_2" : -1,
        "PA_Str" : "6",
        "DMSLat" : "00°46'54.21\" LU",
        "DMSLon" : "125°18'54.43\" BT",
        "NAME" : "Titik ZPPI No. 12 (Zona 6)",
        "PA_Str_1" : "6",
        "PA_Num_1" : 6
      },
      "geometry" : {
        "x" : 125.3151198620001,
        "y" : 0.78172604700002779
      }
    },
    {
      "attributes" : {
        "FID" : 23,
        "FID_AQUA_2" : -1,
        "PA_Str" : "6",
        "DMSLat" : "02°03'35.48\" LU",
        "DMSLon" : "125°40'55.08\" BT",
        "NAME" : "Titik ZPPI No. 13 (Zona 6)",
        "PA_Str_1" : "6",
        "PA_Num_1" : 6
      },
      "geometry" : {
        "x" : 125.68196844500005,
        "y" : 2.0598581840000598
      }
    },
    {
      "attributes" : {
        "FID" : 24,
        "FID_AQUA_2" : -1,
        "PA_Str" : "6",
        "DMSLat" : "01°53'14.35\" LU",
        "DMSLon" : "125°43'26.29\" BT",
        "NAME" : "Titik ZPPI No. 14 (Zona 6)",
        "PA_Str_1" : "6",
        "PA_Num_1" : 6
      },
      "geometry" : {
        "x" : 125.72397000900003,
        "y" : 1.8873220870000509
      }
    },
    {
      "attributes" : {
        "FID" : 25,
        "FID_AQUA_2" : -1,
        "PA_Str" : "6",
        "DMSLat" : "06°39'42.43\" LU",
        "DMSLon" : "125°44'51.02\" BT",
        "NAME" : "Titik ZPPI No. 15 (Zona 6)",
        "PA_Str_1" : "6",
        "PA_Num_1" : 6
      },
      "geometry" : {
        "x" : 125.74750661400003,
        "y" : 6.6617884620001036
      }
    },
    {
      "attributes" : {
        "FID" : 26,
        "FID_AQUA_2" : -1,
        "PA_Str" : "6",
        "DMSLat" : "02°10'10.69\" LU",
        "DMSLon" : "125°47'40.03\" BT",
        "NAME" : "Titik ZPPI No. 16 (Zona 6)",
        "PA_Str_1" : "6",
        "PA_Num_1" : 6
      },
      "geometry" : {
        "x" : 125.79445526000003,
        "y" : 2.1696364350000188
      }
    },
    {
      "attributes" : {
        "FID" : 27,
        "FID_AQUA_2" : -1,
        "PA_Str" : "6",
        "DMSLat" : "02°06'31.26\" LU",
        "DMSLon" : "125°51'25.81\" BT",
        "NAME" : "Titik ZPPI No. 17 (Zona 6)",
        "PA_Str_1" : "6",
        "PA_Num_1" : 6
      },
      "geometry" : {
        "x" : 125.85717177200004,
        "y" : 2.1086837010001105
      }
    },
    {
      "attributes" : {
        "FID" : 28,
        "FID_AQUA_2" : -1,
        "PA_Str" : "6",
        "DMSLat" : "06°30'57.77\" LU",
        "DMSLon" : "125°53'31.18\" BT",
        "NAME" : "Titik ZPPI No. 18 (Zona 6)",
        "PA_Str_1" : "6",
        "PA_Num_1" : 6
      },
      "geometry" : {
        "x" : 125.89199504599999,
        "y" : 6.5160490550000141
      }
    },
    {
      "attributes" : {
        "FID" : 29,
        "FID_AQUA_2" : -1,
        "PA_Str" : "6",
        "DMSLat" : "06°20'36.89\" LU",
        "DMSLon" : "125°53'44.22\" BT",
        "NAME" : "Titik ZPPI No. 19 (Zona 6)",
        "PA_Str_1" : "6",
        "PA_Num_1" : 6
      },
      "geometry" : {
        "x" : 125.89561742600003,
        "y" : 6.3435812350000589
      }
    },
    {
      "attributes" : {
        "FID" : 30,
        "FID_AQUA_2" : -1,
        "PA_Str" : "6",
        "DMSLat" : "01°50'04.26\" LU",
        "DMSLon" : "125°53'57.76\" BT",
        "NAME" : "Titik ZPPI No. 20 (Zona 6)",
        "PA_Str_1" : "6",
        "PA_Num_1" : 6
      },
      "geometry" : {
        "x" : 125.89937817799998,
        "y" : 1.8345176840000335
      }
    },
    {
      "attributes" : {
        "FID" : 31,
        "FID_AQUA_2" : -1,
        "PA_Str" : "6",
        "DMSLat" : "06°15'37.42\" LU",
        "DMSLon" : "126°02'07.90\" BT",
        "NAME" : "Titik ZPPI No. 21 (Zona 6)",
        "PA_Str_1" : "6",
        "PA_Num_1" : 6
      },
      "geometry" : {
        "x" : 126.03552815000015,
        "y" : 6.2603944680000936
      }
    },
    {
      "attributes" : {
        "FID" : 32,
        "FID_AQUA_2" : -1,
        "PA_Str" : "6",
        "DMSLat" : "01°54'28.43\" LU",
        "DMSLon" : "126°05'42.53\" BT",
        "NAME" : "Titik ZPPI No. 22 (Zona 6)",
        "PA_Str_1" : "6",
        "PA_Num_1" : 6
      },
      "geometry" : {
        "x" : 126.09514850300003,
        "y" : 1.9078993790000744
      }
    },
    {
      "attributes" : {
        "FID" : 33,
        "FID_AQUA_2" : -1,
        "PA_Str" : "6",
        "DMSLat" : "01°58'06.11\" LU",
        "DMSLon" : "126°11'29.97\" BT",
        "NAME" : "Titik ZPPI No. 23 (Zona 6)",
        "PA_Str_1" : "6",
        "PA_Num_1" : 6
      },
      "geometry" : {
        "x" : 126.19166019000011,
        "y" : 1.9683660280000872
      }
    },
    {
      "attributes" : {
        "FID" : 34,
        "FID_AQUA_2" : -1,
        "PA_Str" : "6",
        "DMSLat" : "02°01'00.13\" LU",
        "DMSLon" : "126°12'56.12\" BT",
        "NAME" : "Titik ZPPI No. 24 (Zona 6)",
        "PA_Str_1" : "6",
        "PA_Num_1" : 6
      },
      "geometry" : {
        "x" : 126.21559067700001,
        "y" : 2.016703522000082
      }
    },
    {
      "attributes" : {
        "FID" : 35,
        "FID_AQUA_2" : -1,
        "PA_Str" : "6",
        "DMSLat" : "02°00'33.11\" LU",
        "DMSLon" : "126°13'50.22\" BT",
        "NAME" : "Titik ZPPI No. 25 (Zona 6)",
        "PA_Str_1" : "6",
        "PA_Num_1" : 6
      },
      "geometry" : {
        "x" : 126.23061707200011,
        "y" : 2.0091983950000305
      }
    },
    {
      "attributes" : {
        "FID" : 36,
        "FID_AQUA_2" : -1,
        "PA_Str" : "6",
        "DMSLat" : "02°00'06.43\" LU",
        "DMSLon" : "126°17'02.42\" BT",
        "NAME" : "Titik ZPPI No. 26 (Zona 6)",
        "PA_Str_1" : "6",
        "PA_Num_1" : 6
      },
      "geometry" : {
        "x" : 126.28400732600002,
        "y" : 2.0017868040000799
      }
    },
    {
      "attributes" : {
        "FID" : 37,
        "FID_AQUA_2" : -1,
        "PA_Str" : "6",
        "DMSLat" : "02°03'30.70\" LU",
        "DMSLon" : "126°19'38.25\" BT",
        "NAME" : "Titik ZPPI No. 27 (Zona 6)",
        "PA_Str_1" : "6",
        "PA_Num_1" : 6
      },
      "geometry" : {
        "x" : 126.32729225300012,
        "y" : 2.058529796000105
      }
    }
  ]
}