{
  "displayFieldName" : "",
  "fieldAliases" : {
    "FID" : "FID",
    "FID_AQUA_2" : "FID_AQUA_2",
    "PA_Str" : "PA_Str",
    "DMSLat" : "DMSLat",
    "DMSLon" : "DMSLon",
    "NAME" : "NAME",
    "PA_Str_1" : "PA_Str_1",
    "PA_Num_1" : "PA_Num_1"
  },
  "geometryType" : "esriGeometryPoint",
  "spatialReference" : {
    "wkid" : 4326,
    "latestWkid" : 4326
  },
  "fields" : [
    {
      "name" : "FID",
      "type" : "esriFieldTypeOID",
      "alias" : "FID"
    },
    {
      "name" : "FID_AQUA_2",
      "type" : "esriFieldTypeInteger",
      "alias" : "FID_AQUA_2"
    },
    {
      "name" : "PA_Str",
      "type" : "esriFieldTypeString",
      "alias" : "PA_Str",
      "length" : 3
    },
    {
      "name" : "DMSLat",
      "type" : "esriFieldTypeString",
      "alias" : "DMSLat",
      "length" : 254
    },
    {
      "name" : "DMSLon",
      "type" : "esriFieldTypeString",
      "alias" : "DMSLon",
      "length" : 254
    },
    {
      "name" : "NAME",
      "type" : "esriFieldTypeString",
      "alias" : "NAME",
      "length" : 50
    },
    {
      "name" : "PA_Str_1",
      "type" : "esriFieldTypeString",
      "alias" : "PA_Str_1",
      "length" : 3
    },
    {
      "name" : "PA_Num_1",
      "type" : "esriFieldTypeSmallInteger",
      "alias" : "PA_Num_1"
    }
  ],
  "features" : [
    {
      "attributes" : {
        "FID" : 0,
        "FID_AQUA_2" : -1,
        "PA_Str" : "6",
        "DMSLat" : "02°37'07.78\" LU",
        "DMSLon" : "127°35'54.35\" BT",
        "NAME" : "Titik ZPPI No. 1 (Zona 6)",
        "PA_Str_1" : "6",
        "PA_Num_1" : 6
      },
      "geometry" : {
        "x" : 127.59843259100012,
        "y" : 2.618829576000067
      }
    },
    {
      "attributes" : {
        "FID" : 1,
        "FID_AQUA_2" : -1,
        "PA_Str" : "6",
        "DMSLat" : "04°04'50.04\" LU",
        "DMSLon" : "127°36'14.40\" BT",
        "NAME" : "Titik ZPPI No. 2 (Zona 6)",
        "PA_Str_1" : "6",
        "PA_Num_1" : 6
      },
      "geometry" : {
        "x" : 127.60400015700009,
        "y" : 4.0805684120000265
      }
    },
    {
      "attributes" : {
        "FID" : 2,
        "FID_AQUA_2" : -1,
        "PA_Str" : "6",
        "DMSLat" : "04°23'09.45\" LU",
        "DMSLon" : "127°37'19.23\" BT",
        "NAME" : "Titik ZPPI No. 3 (Zona 6)",
        "PA_Str_1" : "6",
        "PA_Num_1" : 6
      },
      "geometry" : {
        "x" : 127.62200933000008,
        "y" : 4.385959738000075
      }
    },
    {
      "attributes" : {
        "FID" : 3,
        "FID_AQUA_2" : -1,
        "PA_Str" : "6",
        "DMSLat" : "04°00'59.54\" LU",
        "DMSLon" : "127°37'56.06\" BT",
        "NAME" : "Titik ZPPI No. 4 (Zona 6)",
        "PA_Str_1" : "6",
        "PA_Num_1" : 6
      },
      "geometry" : {
        "x" : 127.63224088300002,
        "y" : 4.016540015000011
      }
    },
    {
      "attributes" : {
        "FID" : 4,
        "FID_AQUA_2" : -1,
        "PA_Str" : "6",
        "DMSLat" : "04°14'42.98\" LU",
        "DMSLon" : "127°38'27.23\" BT",
        "NAME" : "Titik ZPPI No. 5 (Zona 6)",
        "PA_Str_1" : "6",
        "PA_Num_1" : 6
      },
      "geometry" : {
        "x" : 127.64089942900011,
        "y" : 4.2452734200000144
      }
    },
    {
      "attributes" : {
        "FID" : 5,
        "FID_AQUA_2" : -1,
        "PA_Str" : "6",
        "DMSLat" : "05°18'21.64\" LU",
        "DMSLon" : "127°39'00.44\" BT",
        "NAME" : "Titik ZPPI No. 6 (Zona 6)",
        "PA_Str_1" : "6",
        "PA_Num_1" : 6
      },
      "geometry" : {
        "x" : 127.65012320700009,
        "y" : 5.3060112000000572
      }
    },
    {
      "attributes" : {
        "FID" : 6,
        "FID_AQUA_2" : -1,
        "PA_Str" : "6",
        "DMSLat" : "05°26'34.94\" LU",
        "DMSLon" : "127°40'01.22\" BT",
        "NAME" : "Titik ZPPI No. 7 (Zona 6)",
        "PA_Str_1" : "6",
        "PA_Num_1" : 6
      },
      "geometry" : {
        "x" : 127.66700705400004,
        "y" : 5.4430395570000591
      }
    },
    {
      "attributes" : {
        "FID" : 7,
        "FID_AQUA_2" : -1,
        "PA_Str" : "6",
        "DMSLat" : "02°44'43.55\" LU",
        "DMSLon" : "127°43'51.79\" BT",
        "NAME" : "Titik ZPPI No. 8 (Zona 6)",
        "PA_Str_1" : "6",
        "PA_Num_1" : 6
      },
      "geometry" : {
        "x" : 127.73105468300005,
        "y" : 2.745430563000081
      }
    },
    {
      "attributes" : {
        "FID" : 8,
        "FID_AQUA_2" : -1,
        "PA_Str" : "6",
        "DMSLat" : "04°09'08.02\" LU",
        "DMSLon" : "127°44'59.18\" BT",
        "NAME" : "Titik ZPPI No. 9 (Zona 6)",
        "PA_Str_1" : "6",
        "PA_Num_1" : 6
      },
      "geometry" : {
        "x" : 127.74977483300007,
        "y" : 4.1522294949999896
      }
    },
    {
      "attributes" : {
        "FID" : 9,
        "FID_AQUA_2" : -1,
        "PA_Str" : "6",
        "DMSLat" : "05°32'54.54\" LU",
        "DMSLon" : "127°47'10.50\" BT",
        "NAME" : "Titik ZPPI No. 10 (Zona 6)",
        "PA_Str_1" : "6",
        "PA_Num_1" : 6
      },
      "geometry" : {
        "x" : 127.78625085200008,
        "y" : 5.5484860730000776
      }
    },
    {
      "attributes" : {
        "FID" : 10,
        "FID_AQUA_2" : -1,
        "PA_Str" : "6",
        "DMSLat" : "05°10'09.94\" LU",
        "DMSLon" : "127°47'23.01\" BT",
        "NAME" : "Titik ZPPI No. 11 (Zona 6)",
        "PA_Str_1" : "6",
        "PA_Num_1" : 6
      },
      "geometry" : {
        "x" : 127.78972587800001,
        "y" : 5.1694294340000582
      }
    },
    {
      "attributes" : {
        "FID" : 11,
        "FID_AQUA_2" : -1,
        "PA_Str" : "6",
        "DMSLat" : "04°05'15.07\" LU",
        "DMSLon" : "127°47'45.16\" BT",
        "NAME" : "Titik ZPPI No. 12 (Zona 6)",
        "PA_Str_1" : "6",
        "PA_Num_1" : 6
      },
      "geometry" : {
        "x" : 127.79587831700005,
        "y" : 4.0875219290000899
      }
    },
    {
      "attributes" : {
        "FID" : 12,
        "FID_AQUA_2" : -1,
        "PA_Str" : "6",
        "DMSLat" : "03°29'45.53\" LU",
        "DMSLon" : "127°47'47.47\" BT",
        "NAME" : "Titik ZPPI No. 13 (Zona 6)",
        "PA_Str_1" : "6",
        "PA_Num_1" : 6
      },
      "geometry" : {
        "x" : 127.79651953900009,
        "y" : 3.4959818380000698
      }
    },
    {
      "attributes" : {
        "FID" : 13,
        "FID_AQUA_2" : -1,
        "PA_Str" : "6",
        "DMSLat" : "04°19'32.68\" LU",
        "DMSLon" : "127°47'56.83\" BT",
        "NAME" : "Titik ZPPI No. 14 (Zona 6)",
        "PA_Str_1" : "6",
        "PA_Num_1" : 6
      },
      "geometry" : {
        "x" : 127.7991195650001,
        "y" : 4.3257451890000489
      }
    },
    {
      "attributes" : {
        "FID" : 14,
        "FID_AQUA_2" : -1,
        "PA_Str" : "6",
        "DMSLat" : "03°18'07.15\" LU",
        "DMSLon" : "127°48'39.24\" BT",
        "NAME" : "Titik ZPPI No. 15 (Zona 6)",
        "PA_Str_1" : "6",
        "PA_Num_1" : 6
      },
      "geometry" : {
        "x" : 127.81090054300009,
        "y" : 3.3019861470000436
      }
    },
    {
      "attributes" : {
        "FID" : 15,
        "FID_AQUA_2" : -1,
        "PA_Str" : "6",
        "DMSLat" : "03°31'20.36\" LU",
        "DMSLon" : "127°50'19.27\" BT",
        "NAME" : "Titik ZPPI No. 16 (Zona 6)",
        "PA_Str_1" : "6",
        "PA_Num_1" : 6
      },
      "geometry" : {
        "x" : 127.83868697700009,
        "y" : 3.5223241930000562
      }
    },
    {
      "attributes" : {
        "FID" : 16,
        "FID_AQUA_2" : -1,
        "PA_Str" : "6",
        "DMSLat" : "05°11'29.99\" LU",
        "DMSLon" : "127°50'55.11\" BT",
        "NAME" : "Titik ZPPI No. 17 (Zona 6)",
        "PA_Str_1" : "6",
        "PA_Num_1" : 6
      },
      "geometry" : {
        "x" : 127.84864426,
        "y" : 5.1916651190000742
      }
    },
    {
      "attributes" : {
        "FID" : 17,
        "FID_AQUA_2" : -1,
        "PA_Str" : "6",
        "DMSLat" : "05°13'56.97\" LU",
        "DMSLon" : "127°52'05.93\" BT",
        "NAME" : "Titik ZPPI No. 18 (Zona 6)",
        "PA_Str_1" : "6",
        "PA_Num_1" : 6
      },
      "geometry" : {
        "x" : 127.86831431300001,
        "y" : 5.2324944200000303
      }
    },
    {
      "attributes" : {
        "FID" : 18,
        "FID_AQUA_2" : -1,
        "PA_Str" : "6",
        "DMSLat" : "02°43'50.46\" LU",
        "DMSLon" : "127°54'32.16\" BT",
        "NAME" : "Titik ZPPI No. 19 (Zona 6)",
        "PA_Str_1" : "6",
        "PA_Num_1" : 6
      },
      "geometry" : {
        "x" : 127.90893395300012,
        "y" : 2.7306833690000722
      }
    },
    {
      "attributes" : {
        "FID" : 19,
        "FID_AQUA_2" : -1,
        "PA_Str" : "6",
        "DMSLat" : "05°11'29.57\" LU",
        "DMSLon" : "127°55'35.13\" BT",
        "NAME" : "Titik ZPPI No. 20 (Zona 6)",
        "PA_Str_1" : "6",
        "PA_Num_1" : 6
      },
      "geometry" : {
        "x" : 127.92642737399997,
        "y" : 5.1915496580000244
      }
    },
    {
      "attributes" : {
        "FID" : 20,
        "FID_AQUA_2" : -1,
        "PA_Str" : "6",
        "DMSLat" : "05°35'47.43\" LU",
        "DMSLon" : "127°55'43.82\" BT",
        "NAME" : "Titik ZPPI No. 21 (Zona 6)",
        "PA_Str_1" : "6",
        "PA_Num_1" : 6
      },
      "geometry" : {
        "x" : 127.92884104200002,
        "y" : 5.596509692000037
      }
    },
    {
      "attributes" : {
        "FID" : 21,
        "FID_AQUA_2" : -1,
        "PA_Str" : "6",
        "DMSLat" : "03°27'38.96\" LU",
        "DMSLon" : "127°55'45.04\" BT",
        "NAME" : "Titik ZPPI No. 22 (Zona 6)",
        "PA_Str_1" : "6",
        "PA_Num_1" : 6
      },
      "geometry" : {
        "x" : 127.92918030300011,
        "y" : 3.4608234890001057
      }
    }
  ]
}