{
  "displayFieldName" : "",
  "fieldAliases" : {
    "FID" : "FID",
    "FID_AQUA_2" : "FID_AQUA_2",
    "PA_Str" : "PA_Str",
    "DMSLat" : "DMSLat",
    "DMSLon" : "DMSLon",
    "NAME" : "NAME",
    "PA_Str_1" : "PA_Str_1",
    "PA_Num_1" : "PA_Num_1"
  },
  "geometryType" : "esriGeometryPoint",
  "spatialReference" : {
    "wkid" : 4326,
    "latestWkid" : 4326
  },
  "fields" : [
    {
      "name" : "FID",
      "type" : "esriFieldTypeOID",
      "alias" : "FID"
    },
    {
      "name" : "FID_AQUA_2",
      "type" : "esriFieldTypeInteger",
      "alias" : "FID_AQUA_2"
    },
    {
      "name" : "PA_Str",
      "type" : "esriFieldTypeString",
      "alias" : "PA_Str",
      "length" : 3
    },
    {
      "name" : "DMSLat",
      "type" : "esriFieldTypeString",
      "alias" : "DMSLat",
      "length" : 254
    },
    {
      "name" : "DMSLon",
      "type" : "esriFieldTypeString",
      "alias" : "DMSLon",
      "length" : 254
    },
    {
      "name" : "NAME",
      "type" : "esriFieldTypeString",
      "alias" : "NAME",
      "length" : 50
    },
    {
      "name" : "PA_Str_1",
      "type" : "esriFieldTypeString",
      "alias" : "PA_Str_1",
      "length" : 3
    },
    {
      "name" : "PA_Num_1",
      "type" : "esriFieldTypeSmallInteger",
      "alias" : "PA_Num_1"
    }
  ],
  "features" : [
    {
      "attributes" : {
        "FID" : 176,
        "FID_AQUA_2" : -1,
        "PA_Str" : "14",
        "DMSLat" : "00°49'08.43\" LS",
        "DMSLon" : "124°05'14.86\" BT",
        "NAME" : "Titik ZPPI No. 1 (Zona 14)",
        "PA_Str_1" : "14",
        "PA_Num_1" : 14
      },
      "geometry" : {
        "x" : 124.08746131400005,
        "y" : -0.81901067099991387
      }
    },
    {
      "attributes" : {
        "FID" : 177,
        "FID_AQUA_2" : -1,
        "PA_Str" : "14",
        "DMSLat" : "00°38'35.08\" LS",
        "DMSLon" : "124°07'58.40\" BT",
        "NAME" : "Titik ZPPI No. 2 (Zona 14)",
        "PA_Str_1" : "14",
        "PA_Num_1" : 14
      },
      "geometry" : {
        "x" : 124.13288923400009,
        "y" : -0.64308050299991848
      }
    },
    {
      "attributes" : {
        "FID" : 178,
        "FID_AQUA_2" : -1,
        "PA_Str" : "14",
        "DMSLat" : "00°01'22.55\" LS",
        "DMSLon" : "125°41'23.07\" BT",
        "NAME" : "Titik ZPPI No. 3 (Zona 14)",
        "PA_Str_1" : "14",
        "PA_Num_1" : 14
      },
      "geometry" : {
        "x" : 125.68974265800009,
        "y" : -0.022932761999886253
      }
    },
    {
      "attributes" : {
        "FID" : 179,
        "FID_AQUA_2" : -1,
        "PA_Str" : "14",
        "DMSLat" : "00°08'03.86\" LS",
        "DMSLon" : "126°15'56.78\" BT",
        "NAME" : "Titik ZPPI No. 4 (Zona 14)",
        "PA_Str_1" : "14",
        "PA_Num_1" : 14
      },
      "geometry" : {
        "x" : 126.26577393300013,
        "y" : -0.13440576200000365
      }
    },
    {
      "attributes" : {
        "FID" : 180,
        "FID_AQUA_2" : -1,
        "PA_Str" : "14",
        "DMSLat" : "00°02'04.48\" LS",
        "DMSLon" : "126°16'48.58\" BT",
        "NAME" : "Titik ZPPI No. 5 (Zona 14)",
        "PA_Str_1" : "14",
        "PA_Num_1" : 14
      },
      "geometry" : {
        "x" : 126.28016359900005,
        "y" : -0.03457861099997217
      }
    }
  ]
}