{
  "displayFieldName" : "",
  "fieldAliases" : {
    "FID" : "FID",
    "FID_TERRA_" : "FID_TERRA_",
    "PA_Str" : "PA_Str",
    "DMSLat" : "DMSLat",
    "DMSLon" : "DMSLon",
    "NAME" : "NAME",
    "PA_Str_1" : "PA_Str_1",
    "PA_Num_1" : "PA_Num_1"
  },
  "geometryType" : "esriGeometryPoint",
  "spatialReference" : {
    "wkid" : 4326,
    "latestWkid" : 4326
  },
  "fields" : [
    {
      "name" : "FID",
      "type" : "esriFieldTypeOID",
      "alias" : "FID"
    },
    {
      "name" : "FID_TERRA_",
      "type" : "esriFieldTypeInteger",
      "alias" : "FID_TERRA_"
    },
    {
      "name" : "PA_Str",
      "type" : "esriFieldTypeString",
      "alias" : "PA_Str",
      "length" : 3
    },
    {
      "name" : "DMSLat",
      "type" : "esriFieldTypeString",
      "alias" : "DMSLat",
      "length" : 254
    },
    {
      "name" : "DMSLon",
      "type" : "esriFieldTypeString",
      "alias" : "DMSLon",
      "length" : 254
    },
    {
      "name" : "NAME",
      "type" : "esriFieldTypeString",
      "alias" : "NAME",
      "length" : 50
    },
    {
      "name" : "PA_Str_1",
      "type" : "esriFieldTypeString",
      "alias" : "PA_Str_1",
      "length" : 3
    },
    {
      "name" : "PA_Num_1",
      "type" : "esriFieldTypeSmallInteger",
      "alias" : "PA_Num_1"
    }
  ],
  "features" : [
    {
      "attributes" : {
        "FID" : 0,
        "FID_TERRA_" : -1,
        "PA_Str" : "6",
        "DMSLat" : "05°09'56.80\" LU",
        "DMSLon" : "124°19'57.64\" BT",
        "NAME" : "Titik ZPPI No. 1 (Zona 6)",
        "PA_Str_1" : "6",
        "PA_Num_1" : 6
      },
      "geometry" : {
        "x" : 124.33267928400002,
        "y" : 5.1657788900000803
      }
    },
    {
      "attributes" : {
        "FID" : 1,
        "FID_TERRA_" : -1,
        "PA_Str" : "6",
        "DMSLat" : "05°07'43.40\" LU",
        "DMSLon" : "124°24'02.41\" BT",
        "NAME" : "Titik ZPPI No. 2 (Zona 6)",
        "PA_Str_1" : "6",
        "PA_Num_1" : 6
      },
      "geometry" : {
        "x" : 124.4006704010001,
        "y" : 5.1287228620000427
      }
    },
    {
      "attributes" : {
        "FID" : 2,
        "FID_TERRA_" : -1,
        "PA_Str" : "6",
        "DMSLat" : "05°07'41.71\" LU",
        "DMSLon" : "124°24'52.20\" BT",
        "NAME" : "Titik ZPPI No. 3 (Zona 6)",
        "PA_Str_1" : "6",
        "PA_Num_1" : 6
      },
      "geometry" : {
        "x" : 124.41450145700006,
        "y" : 5.1282541140000717
      }
    },
    {
      "attributes" : {
        "FID" : 3,
        "FID_TERRA_" : -1,
        "PA_Str" : "6",
        "DMSLat" : "05°08'26.12\" LU",
        "DMSLon" : "124°30'45.86\" BT",
        "NAME" : "Titik ZPPI No. 4 (Zona 6)",
        "PA_Str_1" : "6",
        "PA_Num_1" : 6
      },
      "geometry" : {
        "x" : 124.51273953400006,
        "y" : 5.1405896670000253
      }
    },
    {
      "attributes" : {
        "FID" : 4,
        "FID_TERRA_" : -1,
        "PA_Str" : "6",
        "DMSLat" : "05°10'59.54\" LU",
        "DMSLon" : "124°32'09.82\" BT",
        "NAME" : "Titik ZPPI No. 5 (Zona 6)",
        "PA_Str_1" : "6",
        "PA_Num_1" : 6
      },
      "geometry" : {
        "x" : 124.53606127700004,
        "y" : 5.1832075470000873
      }
    },
    {
      "attributes" : {
        "FID" : 5,
        "FID_TERRA_" : -1,
        "PA_Str" : "6",
        "DMSLat" : "05°03'47.85\" LU",
        "DMSLon" : "124°47'54.21\" BT",
        "NAME" : "Titik ZPPI No. 6 (Zona 6)",
        "PA_Str_1" : "6",
        "PA_Num_1" : 6
      },
      "geometry" : {
        "x" : 124.79839432200001,
        "y" : 5.0632917370000499
      }
    },
    {
      "attributes" : {
        "FID" : 6,
        "FID_TERRA_" : -1,
        "PA_Str" : "6",
        "DMSLat" : "05°10'08.80\" LU",
        "DMSLon" : "124°48'59.46\" BT",
        "NAME" : "Titik ZPPI No. 7 (Zona 6)",
        "PA_Str_1" : "6",
        "PA_Num_1" : 6
      },
      "geometry" : {
        "x" : 124.81651778900005,
        "y" : 5.1691137150000479
      }
    },
    {
      "attributes" : {
        "FID" : 7,
        "FID_TERRA_" : -1,
        "PA_Str" : "6",
        "DMSLat" : "05°00'12.49\" LU",
        "DMSLon" : "124°57'03.13\" BT",
        "NAME" : "Titik ZPPI No. 8 (Zona 6)",
        "PA_Str_1" : "6",
        "PA_Num_1" : 6
      },
      "geometry" : {
        "x" : 124.95087201400013,
        "y" : 5.0034702910000419
      }
    },
    {
      "attributes" : {
        "FID" : 8,
        "FID_TERRA_" : -1,
        "PA_Str" : "6",
        "DMSLat" : "02°08'52.89\" LU",
        "DMSLon" : "126°06'24.96\" BT",
        "NAME" : "Titik ZPPI No. 9 (Zona 6)",
        "PA_Str_1" : "6",
        "PA_Num_1" : 6
      },
      "geometry" : {
        "x" : 126.10693530300014,
        "y" : 2.1480254690000891
      }
    },
    {
      "attributes" : {
        "FID" : 9,
        "FID_TERRA_" : -1,
        "PA_Str" : "6",
        "DMSLat" : "02°12'48.05\" LU",
        "DMSLon" : "126°15'06.82\" BT",
        "NAME" : "Titik ZPPI No. 10 (Zona 6)",
        "PA_Str_1" : "6",
        "PA_Num_1" : 6
      },
      "geometry" : {
        "x" : 126.25189718700003,
        "y" : 2.21334993700005
      }
    },
    {
      "attributes" : {
        "FID" : 10,
        "FID_TERRA_" : -1,
        "PA_Str" : "6",
        "DMSLat" : "02°31'18.51\" LU",
        "DMSLon" : "127°56'35.79\" BT",
        "NAME" : "Titik ZPPI No. 11 (Zona 6)",
        "PA_Str_1" : "6",
        "PA_Num_1" : 6
      },
      "geometry" : {
        "x" : 127.94327628500005,
        "y" : 2.5218092230000124
      }
    }
  ]
}